peanut_config.py
tsk.py
tsk_enhanced.py
tusktsk/__init__.py
tusktsk/peanut_config.py
tusktsk/tsk.py
tusktsk/tsk_enhanced.py
tusktsk-2.0.1.dist-info/METADATA
tusktsk-2.0.1.dist-info/WHEEL
tusktsk-2.0.1.dist-info/entry_points.txt
tusktsk-2.0.1.dist-info/top_level.txt
tusktsk-2.0.1.dist-info/RECORD
