Metadata-Version: 2.4
Name: tusktsk
Version: 2.0.1
Summary: TuskTsk - Configuration with a Heartbeat
Home-page: https://github.com/cyber-boost/tusktsk
Author: Cyberboost LLC
Author-email: Cyberboost LLC <packages@tuskt.sk>
Project-URL: Homepage, https://tuskt.sk
Project-URL: Bug Tracker, https://github.com/cyber-boost/tusktsk/issues
Project-URL: License, https://tuskt.sk/license
Classifier: Programming Language :: Python :: 3
Classifier: Operating System :: OS Independent
Requires-Python: >=3.8, <4
Requires-Dist: msgpack>=1.0.0
Requires-Dist: watchdog>=2.0.0
Provides-Extra: dev
Requires-Dist: pytest>=6.0; extra == "dev"
Requires-Dist: black; extra == "dev"
Requires-Dist: flake8; extra == "dev"
Provides-Extra: databases
Requires-Dist: psycopg2-binary>=2.8; extra == "databases"
Requires-Dist: pymongo>=3.11; extra == "databases"
Requires-Dist: redis>=3.5; extra == "databases"
Dynamic: author
Dynamic: home-page
Dynamic: requires-python
